nb2py.py
py2nb.py
py2nb-1.1.1.data/scripts/nb2py
py2nb-1.1.1.data/scripts/py2nb
py2nb-1.1.1.dist-info/licenses/LICENSE
py2nb-1.1.1.dist-info/METADATA
py2nb-1.1.1.dist-info/WHEEL
py2nb-1.1.1.dist-info/top_level.txt
py2nb-1.1.1.dist-info/RECORD
